pyzuh/__init__.py
pyzuh/active_response.py
pyzuh/agents.py
pyzuh/authentication.py
pyzuh/ciscat.py
pyzuh/cluster.py
pyzuh/decoders.py
pyzuh/errors.py
pyzuh/events.py
pyzuh/experimental.py
pyzuh/groups.py
pyzuh/lists.py
pyzuh/logtest.py
pyzuh/manager.py
pyzuh/mitre.py
pyzuh/overview.py
pyzuh/rootcheck.py
pyzuh/rules.py
pyzuh/sca.py
pyzuh/security.py
pyzuh/syscheck.py
pyzuh/tasks.py
pyzuh-1.0.0.dist-info/METADATA
pyzuh-1.0.0.dist-info/WHEEL
pyzuh-1.0.0.dist-info/RECORD
