Metadata-Version: 2.1
Name: pyzuh
Version: 1.0.0
Summary: Python Library for the Wazuh API
Home-page: https://github.com/Lilium48/pyzuh
License: MIT
Author: Austin Silano
Author-email: austin@liliumsecurity.com
Requires-Python: >=3.6,<4.0
Classifier: License :: OSI Approved :: MIT License
Classifier: Programming Language :: Python :: 3
Classifier: Programming Language :: Python :: 3.6
Classifier: Programming Language :: Python :: 3.7
Classifier: Programming Language :: Python :: 3.8
Classifier: Programming Language :: Python :: 3.9
Classifier: Programming Language :: Python :: 3.10
Classifier: Programming Language :: Python :: 3.11
Classifier: Programming Language :: Python :: 3.12
Requires-Dist: pyjwt (>=2.8.0)
Requires-Dist: requests (>=2.31.0)
Requires-Dist: urllib3 (>=2.2.0)
